{
  "title": "신랑 신부에게 마음을 전해주세요.",
  "description": "감사한 마음 잊지 않고 오랫동안 간직할게요.",
  "groom": [
    {
      "holderName": "백미정",
      "bankName": "카카오뱅크",
      "accountNumber": "3333-19-9315738",
      "logo": "/assets/svg/kakaobank.svg"
    },
    {
      "holderName": "송요섭",
      "bankName": "신한은행",
      "accountNumber": "110-308-732355",
      "logo": "/assets/svg/shinhan.svg"
    }
  ],
  "bridge": [
    {
      "holderName": "김옥현",
      "bankName": "NH농협",
      "accountNumber": "307044-56-068824",
      "logo": "/assets/svg/nh.svg"
    },
    {
      "holderName": "이누리",
      "bankName": "신한은행",
      "accountNumber": "110-398-944403",
      "logo": "/assets/svg/shinhan.svg"
    }
  ]
}